ultraspn/__init__.py
ultraspn/_version.py
ultraspn/camera_controller.py
ultraspn/controller.py
ultraspn/manager.py
ultraspn/processor.py
ultraspn-0.0.7.post1.dist-info/METADATA
ultraspn-0.0.7.post1.dist-info/WHEEL
ultraspn-0.0.7.post1.dist-info/top_level.txt
ultraspn-0.0.7.post1.dist-info/RECORD
