Metadata-Version: 2.4
Name: ultraspn
Version: 0.0.7.post1
Summary: UltraSPN: An open-source toolbox for automated analysis of compression test images using computer vision
Author-email: Zhiyuan Chen <this@zyc.ai>, Zixiang Zhou <zixiangzhou163@163.com>, Zehuan Huang <huangzehuan@163.com>
Maintainer-email: Zhiyuan Chen <this@zyc.ai>
Project-URL: documentation, https://ultraspn.danling.org
Project-URL: homepage, https://ultraspn.danling.org
Project-URL: repository, https://github.com/MultiMolecule/UltraSPN
Keywords: hydrogel,polymer,compression-testing,computer-vision
Classifier: Development Status :: 2 - Pre-Alpha
Classifier: Intended Audience :: Developers
Classifier: Intended Audience :: Education
Classifier: Intended Audience :: Science/Research
Classifier: License :: OSI Approved :: GNU Affero General Public License v3 or later (AGPLv3+)
Classifier: Operating System :: OS Independent
Classifier: Programming Language :: Python :: 3 :: Only
Classifier: Programming Language :: Python :: 3.7
Classifier: Programming Language :: Python :: 3.8
Classifier: Programming Language :: Python :: 3.9
Classifier: Programming Language :: Python :: 3.10
Classifier: Programming Language :: Python :: 3.11
Classifier: Programming Language :: Python :: 3.12
Classifier: Programming Language :: Python :: 3.13
Classifier: Topic :: Scientific/Engineering :: Artificial Intelligence
Requires-Python: >=3.7
Requires-Dist: chanfig
Requires-Dist: pandas
Requires-Dist: numpy
Requires-Dist: opencv-python-headless
Requires-Dist: Pillow
